chronophore/__init__.py
chronophore/__main__.py
chronophore/chronophore.py
chronophore/config.py
chronophore/controller.py
chronophore/models.py
chronophore/qtview.py
chronophore/tkview.py
chronophore-0.6.0.dist-info/DESCRIPTION.rst
chronophore-0.6.0.dist-info/METADATA
chronophore-0.6.0.dist-info/RECORD
chronophore-0.6.0.dist-info/WHEEL
chronophore-0.6.0.dist-info/entry_points.txt
chronophore-0.6.0.dist-info/metadata.json
chronophore-0.6.0.dist-info/top_level.txt
