Metadata-Version: 2.0
Name: chronophore
Version: 0.6.0
Summary: Desktop app for tracking sign-ins and sign-outs in a tutoring center.
Home-page: https://github.com/mesbahamin/chronophore
Author: Amin Mesbah
Author-email: mesbahamin@gmail.com
License: MIT
Keywords: database desktop education sqlite kiosk sign-in time qt
Platform: UNKNOWN
Classifier: Development Status :: 3 - Alpha
Classifier: Intended Audience :: Education
Classifier: Intended Audience :: End Users/Desktop
Classifier: Topic :: Office/Business :: Scheduling
Classifier: License :: OSI Approved :: MIT License
Classifier: Natural Language :: English
Classifier: Operating System :: Microsoft :: Windows :: Windows 7
Classifier: Operating System :: POSIX :: Linux
Classifier: Programming Language :: Python :: 3 :: Only
Classifier: Programming Language :: Python :: 3.4
Classifier: Programming Language :: Python :: 3.5
Classifier: Programming Language :: Python :: Implementation :: CPython
Requires-Dist: SQLAlchemy (>=1.1.2)
Requires-Dist: appdirs (>=1.4.0)
Requires-Dist: chronophore[qt]
Requires-Dist: openpyxl (>=2.3.5)
Provides-Extra: dev
Requires-Dist: flake8; extra == 'dev'
Provides-Extra: qt
Requires-Dist: PyQt5 (>=5.7); extra == 'qt'
Provides-Extra: test
Requires-Dist: pytest; extra == 'test'
